hill_cipher/__init__.py
hill_cipher/hill_cipher.py
hill_cipher_lib-0.1.0.dist-info/licenses/LICENSE
hill_cipher_lib-0.1.0.dist-info/METADATA
hill_cipher_lib-0.1.0.dist-info/WHEEL
hill_cipher_lib-0.1.0.dist-info/top_level.txt
hill_cipher_lib-0.1.0.dist-info/RECORD
