Metadata-Version: 2.4
Name: hill-cipher-lib
Version: 0.1.0
Summary: A simple implementation of the Hill Cipher encryption and decryption.
Author-email: Mokesh <mokesh0606@gmail.com>
License: MIT
Requires-Python: >=3.7
License-File: LICENSE
Requires-Dist: numpy
Dynamic: license-file
